[
  {
    "id": 0,
    "skillName": "Spoken Languages",
    "description": [
      "🇩🇪 German - Native",
      "🇬🇧 English - Proficient",
      "🇫🇷 French - Intermediate",
      "🇮🇹 Italian - Elementary",
      "🇪🇸 Spanish - Elementary"
    ]
  },
  {
    "id": 1,
    "skillName": "Platforms",
    "description": ["Windows", "Linux", "Atmega", "WinCC", "Microcontroller"]
  },
  {
    "id": 2,
    "skillName": "Coding",
    "description": ["C++", "Javascript", "HTML", "CSS/ SASS", "NodeJS", "React"]
  },
  {
    "id": 3,
    "skillName": "Applications",
    "description": ["Office package", "Adobe", "GitHub", "Trello"]
  }
]
